{
  "date": "2025-10-08",
  "execution_time": "2025-10-08 16:39:23",
  "tasks_completed": [
    "Added API validation before webhook call",
    "Integrated DPR with internal dashboard",
    "Improve error handling and logging",
    "Optimize webhook response time",
    "Setup daily automation"
  ],
  "issues_faced": [
    "n8n node connection error"
  ],
  "next_plan": [
    "Store DPR in PostgreSQL database",
    "Enable AI-based task suggestion in DPR"
  ],
  "key_learnings": [
    "Gained experience in API response validation"
  ],
  "insights": [
    "n8n + Python = powerful workflow automation stack"
  ],
  "sent_at": "2025-10-08 16:39:23"
}